{
  "type": "array",
  "items": {
    "type": "object",
    "properties": {
      "x": {
        "oneOf": [
          {
            "type": "number"
          },
          {
            "type": "null"
          }
        ]
      },
      "y": {
        "oneOf": [
          {
            "type": "number"
          },
          {
            "type": "null"
          }
        ]
      },
      "radius": {
        "type": "number"
      },
      "color": {
        "type": "string"
      },
      "label": {
        "oneOf": [
          {
            "type": "number"
          },
          {
            "type": "string"
          }
        ]
      },
      "data": {
        "type": "object"
      }
    }
  }
}